README.rst
hourbike.py
setup.py
hourbike_cli.egg-info/PKG-INFO
hourbike_cli.egg-info/SOURCES.txt
hourbike_cli.egg-info/dependency_links.txt
hourbike_cli.egg-info/entry_points.txt
hourbike_cli.egg-info/requires.txt
hourbike_cli.egg-info/top_level.txt