Metadata-Version: 1.1
Name: hourbike-cli
Version: 1.0
Summary: A CLI for Hourbike schemes across the UK
Home-page: https://github.com/GreenTurtwig/hourbike-cli
Author: GreenTurtwig
Author-email: UNKNOWN
License: MIT
Keywords: cli bike bicycle hire
Platform: UNKNOWN
Classifier: Intended Audience :: End Users/Desktop
Classifier: License :: OSI Approved :: MIT License
Classifier: Programming Language :: Python :: 2.7
Classifier: Programming Language :: Python :: 3.5
Classifier: Topic :: Utilities
